haikus/__init__.py
haikus/kigo.json
haikus/main.py
haikus-0.3.8.dist-info/METADATA
haikus-0.3.8.dist-info/WHEEL
haikus-0.3.8.dist-info/top_level.txt
haikus-0.3.8.dist-info/RECORD
