Metadata-Version: 2.1
Name: haikus
Version: 0.3.8
Summary: A Python package for analyzing haikus.
Home-page: https://github.com/ituyama/haikus
Author: YAMANO Itsuki
License: CC BY-SA 4.0
Classifier: Programming Language :: Python :: 3.6
Requires-Dist: pykakasi
